ojet/__init__.py
ojet-0.11.5.dist-info/LICENSE
ojet-0.11.5.dist-info/METADATA
ojet-0.11.5.dist-info/WHEEL
ojet-0.11.5.dist-info/top_level.txt
ojet-0.11.5.dist-info/RECORD
