Metadata-Version: 2.1
Name: ojet
Version: 0.11.5
Summary: ojet: a wrapper around Oracle JET
Home-page: https://github.com/gdsc/ojet
Author: Gerard DUVAL
Author-email: gduvalsc@gmail.com
License: UNKNOWN
Project-URL: Bug Tracker, https://github.com/gdsc/ojet/issues
Platform: UNKNOWN
Classifier: Programming Language :: Python :: 3
Classifier: License :: OSI Approved :: MIT License
Classifier: Operating System :: OS Independent
Requires-Python: >=3.6
License-File: LICENSE
